SteamTracker/SteamPricer.py
SteamTracker/__init__.py
Steam_Price-0.0.1.dist-info/LICENCE
Steam_Price-0.0.1.dist-info/METADATA
Steam_Price-0.0.1.dist-info/WHEEL
Steam_Price-0.0.1.dist-info/top_level.txt
Steam_Price-0.0.1.dist-info/RECORD
